django_oidc_user/__init__.py
django_oidc_user/admin.py
django_oidc_user/apps.py
django_oidc_user/locales.py
django_oidc_user/models.py
django_oidc_user/oidc_provider.py
django_oidc_user/timezones.py
django_oidc_user/migrations/0001_initial.py
django_oidc_user/migrations/0002_add_is_verified_field.py
django_oidc_user/migrations/0003_fix_locales.py
django_oidc_user/migrations/0004_alter_user_id.py
django_oidc_user/migrations/__init__.py
django_oidc_user-0.3.6.dist-info/LICENSE
django_oidc_user-0.3.6.dist-info/METADATA
django_oidc_user-0.3.6.dist-info/WHEEL
django_oidc_user-0.3.6.dist-info/top_level.txt
django_oidc_user-0.3.6.dist-info/RECORD
