Metadata-Version: 2.1
Name: django-oidc-user
Version: 0.3.6
Summary: Creates an OpenID Connect compliant User model.
Home-page: https://github.com/montudor/django-oidc-user
Download-URL: https://github.com/montudor/django-oidc-user/archive/v0.3.4.tar.gz
Author: Monte Hellawell
Author-email: monte@montudor.com
Keywords: django
Classifier: Programming Language :: Python :: 3
Classifier: License :: OSI Approved :: MIT License
License-File: LICENSE
